speedinfo/__init__.py
speedinfo/admin.py
speedinfo/apps.py
speedinfo/backends.py
speedinfo/conditions/__init__.py
speedinfo/conditions/base.py
speedinfo/conditions/dispatcher.py
speedinfo/conditions/exclude_urls.py
speedinfo/conf.py
speedinfo/managers.py
speedinfo/middleware.py
speedinfo/models.py
speedinfo/profiler.py
speedinfo/static/speedinfo/css/admin.css
speedinfo/static/speedinfo/img/icon-turned-off.svg
speedinfo/static/speedinfo/img/icon-turned-on.svg
speedinfo/static/speedinfo/js/jquery.fixed-table-header.js
speedinfo/storage/__init__.py
speedinfo/storage/base.py
speedinfo/storage/cache/__init__.py
speedinfo/storage/cache/storage.py
speedinfo/storage/database/__init__.py
speedinfo/storage/database/migrations/0001_initial.py
speedinfo/storage/database/migrations/__init__.py
speedinfo/storage/database/models.py
speedinfo/storage/database/storage.py
speedinfo/templates/admin/speedinfo/change_list.html
speedinfo/templates/admin/speedinfo/dice_chart.html
speedinfo/utils.py
django_speedinfo-2.0.2.dist-info/LICENSE
django_speedinfo-2.0.2.dist-info/WHEEL
django_speedinfo-2.0.2.dist-info/METADATA
django_speedinfo-2.0.2.dist-info/RECORD
